mcddns/__init__.py
mcddns/cli.py
mcddns/exceptions.py
mcddns/provider/__init__.py
mcddns/provider/mcddns_aws.py
mcddns/provider/mcddns_dyn.py
mcddns/provider/mcddns_google.py
mcddns/provider/mcddns_ipify.py
mcddns-1.2.0.dist-info/entry_points.txt
mcddns-1.2.0.dist-info/WHEEL
mcddns-1.2.0.dist-info/METADATA
mcddns-1.2.0.dist-info/RECORD
