Metadata-Version: 2.1
Name: mcddns
Version: 1.2.0
Summary: Industrial-strength dynamic DNS client
Home-page: https://github.com/mconigliaro/mcddns
Author: Mike Conigliaro
Author-email: mike@conigliaro.org
Requires-Python: >=3.8,<4.0
Classifier: Development Status :: 5 - Production/Stable
Classifier: Environment :: Console
Classifier: Intended Audience :: Information Technology
Classifier: Intended Audience :: System Administrators
Classifier: License :: OSI Approved :: MIT License
Classifier: Natural Language :: English
Classifier: Operating System :: OS Independent
Classifier: Programming Language :: Python :: 3
Classifier: Programming Language :: Python :: 3.10
Classifier: Programming Language :: Python :: 3.8
Classifier: Programming Language :: Python :: 3.9
Classifier: Topic :: Internet :: Name Service (DNS)
Classifier: Topic :: System :: Systems Administration
Requires-Dist: boto3 (>=1.23,<2.0)
Requires-Dist: requests (>=2.27,<3.0)
Project-URL: Repository, https://github.com/mconigliaro/mcddns
